.gitignore
LICENSE
README.rst
install.sh
pyproject.toml
setup.cfg
setup.py
docs/Makefile
docs/make_pdf.sh
docs/readme.rst
docs/source/bib.rst
docs/source/conclusion.rst
docs/source/conf.py
docs/source/examples.rst
docs/source/how_to_use.rst
docs/source/index.rst
docs/source/intro.rst
docs/source/preamble.tex
docs/source/sphinxkit.sty
docs/source/_static/ans.bst
docs/source/_static/hpmc.bib
docs/source/_static/tsp.bib
docs/source/examples/all.sh
docs/source/examples/alphanum.res.t
docs/source/examples/alphanum.t
docs/source/examples/eva1.res.t
docs/source/examples/eva1.t
docs/source/examples/eva1.txt
docs/source/examples/exe1.res.t
docs/source/examples/exe1.t
docs/source/examples/firstline1.res.t
docs/source/examples/firstline1.t
docs/source/examples/firstline2.res.t
docs/source/examples/firstline2.t
docs/source/examples/firstline3.res.t
docs/source/examples/firstline3.t
docs/source/examples/incl.txt
docs/source/examples/incl1.res.t
docs/source/examples/incl1.t
docs/source/examples/incl2.res.t
docs/source/examples/incl2.t
docs/source/examples/intro.res.t
docs/source/examples/intro.t
docs/source/examples/itempl.txt
docs/source/examples/keys1.res.t
docs/source/examples/keys1.t
docs/source/examples/keys2.res.t
docs/source/examples/keys2.t
docs/source/examples/log.alphanum.t
docs/source/examples/log.eva1.t
docs/source/examples/log.exe1.t
docs/source/examples/log.firstline1.t
docs/source/examples/log.firstline2.t
docs/source/examples/log.firstline3.t
docs/source/examples/log.incl1.t
docs/source/examples/log.incl2.t
docs/source/examples/log.intro.t
docs/source/examples/log.keys1.t
docs/source/examples/log.keys2.t
docs/source/examples/log.main.t
docs/source/examples/log.mline1.t
docs/source/examples/log.mline2.t
docs/source/examples/log.mline3.t
docs/source/examples/log.mline4.t
docs/source/examples/log.mline5.t
docs/source/examples/log.mline6.t
docs/source/examples/log.mline_eval.t
docs/source/examples/log.param1-.t
docs/source/examples/log.param1._0.t
twps.egg-info/PKG-INFO
twps.egg-info/SOURCES.txt
twps.egg-info/dependency_links.txt
twps.egg-info/top_level.txt